ophac/__init__.py
ophac/dendrogram.py
ophac/dtypes.py
ophac/hac.py
ophac/json_support.py
ophac/rnd.py
ophac/ultrametric.py
ophac_pkg_danielbakkelund-0.1.0.dist-info/METADATA
ophac_pkg_danielbakkelund-0.1.0.dist-info/WHEEL
ophac_pkg_danielbakkelund-0.1.0.dist-info/top_level.txt
ophac_pkg_danielbakkelund-0.1.0.dist-info/RECORD
